LICENSE
MANIFEST.in
README.rst
setup.py
signaller.py
Signaller.egg-info/PKG-INFO
Signaller.egg-info/SOURCES.txt
Signaller.egg-info/dependency_links.txt
Signaller.egg-info/top_level.txt