Metadata-Version: 1.1
Name: Signaller
Version: 1.0.0
Summary: Signals and slots implementation with asyncio support
Home-page: https://github.com/xmikos/signaller
Author: Michal Krenek (Mikos)
Author-email: m.krenek@gmail.com
License: MIT
Keywords: signal slot dispatch dispatcher observer event notify asyncio weakref
Platform: UNKNOWN
Classifier: Development Status :: 5 - Production/Stable
Classifier: Intended Audience :: Developers
Classifier: License :: OSI Approved :: MIT License
Classifier: Natural Language :: English
Classifier: Operating System :: OS Independent
Classifier: Programming Language :: Python :: 3
Classifier: Topic :: Software Development :: Libraries :: Python Modules
